{
  "blog_post": {
    "content": "Only 1 units of Standing Desk (SKU: FU-002) remaining. We will place the reorder during non-carbon hours to minimize environmental impact.",
    "title": "Low Stock Alert: Standing Desk"
  },
  "email": {
    "to": "ajithdschrozahan@gmail.com",
    "subject": "Low Stock Alert: Standing Desk (SKU: FU-002) \u2014 only 1 units left",
    "body": "Please prepare to restock Standing Desk (SKU: FU-002). Current stock is critically low at 1 units. We will place the order during non-carbon hours to minimize environmental impact."
  },
  "calendar_meeting": {
    "start": "2026-04-08T09:00:00",
    "description": "Review restock plan for Standing Desk. Current stock is critically low at 1 units.",
    "summary": "Restock Review: Standing Desk",
    "end": "2026-04-08T09:30:00",
    "attendee_emails": [
      "ajithdschrozahan@gmail.com"
    ]
  }
}